{
  "format": "songwalker-preset",
  "version": 1,
  "name": "Shanai",
  "category": "sampler",
  "tags": [
    "melodic",
    "ethnic",
    "gm:111",
    "sustained",
    "looped"
  ],
  "metadata": {
    "gmProgram": 111,
    "gmCategory": "ethnic",
    "source": "SoundBlasterOld",
    "variant": 0,
    "license": "See original SF2 license"
  },
  "node": {
    "type": "sampler",
    "config": {
      "oneShot": false,
      "zones": [
        {
          "keyRange": {
            "low": 0,
            "high": 115
          },
          "pitch": {
            "rootNote": 93,
            "fineTuneCents": 71
          },
          "sampleRate": 44100,
          "audio": {
            "type": "external",
            "url": "zone_A6.raw",
            "codec": "raw",
            "sha256": "d8a05034cbc2ad77"
          },
          "loop": {
            "start": 1805,
            "end": 1853
          }
        },
        {
          "keyRange": {
            "low": 116,
            "high": 127
          },
          "pitch": {
            "rootNote": 111,
            "fineTuneCents": 48
          },
          "sampleRate": 44100,
          "audio": {
            "type": "external",
            "url": "zone_Eb8.raw",
            "codec": "raw",
            "sha256": "4d1627b88d666760"
          },
          "loop": {
            "start": 2963,
            "end": 5394
          }
        }
      ]
    }
  }
}