{
  "format": "songwalker-preset",
  "version": 1,
  "name": "Overdriven Guitar",
  "category": "sampler",
  "tags": [
    "melodic",
    "guitar",
    "gm:29",
    "sustained",
    "looped"
  ],
  "metadata": {
    "gmProgram": 29,
    "gmCategory": "guitar",
    "source": "SoundBlasterOld",
    "variant": 1,
    "license": "See original SF2 license"
  },
  "node": {
    "type": "sampler",
    "config": {
      "oneShot": false,
      "zones": [
        {
          "keyRange": {
            "low": 0,
            "high": 109
          },
          "pitch": {
            "rootNote": 87,
            "fineTuneCents": 18
          },
          "sampleRate": 44100,
          "audio": {
            "type": "external",
            "url": "zone_Eb6.raw",
            "codec": "raw",
            "sha256": "7c9a2382ee2618c2"
          },
          "loop": {
            "start": 9,
            "end": 114
          }
        },
        {
          "keyRange": {
            "low": 110,
            "high": 127
          },
          "pitch": {
            "rootNote": 111,
            "fineTuneCents": 48
          },
          "sampleRate": 44100,
          "audio": {
            "type": "external",
            "url": "zone_Eb8.raw",
            "codec": "raw",
            "sha256": "4d1627b88d666760"
          },
          "loop": {
            "start": 2963,
            "end": 5394
          }
        }
      ]
    }
  }
}